[
    {
        "type": "message",
        "text": "",
        "files": [
            {
                "id": "FR77H50RM",
                "created": 1575248733,
                "timestamp": 1575248733,
                "name": "IMG-20191201-WA0004.jpg",
                "title": "IMG-20191201-WA0004.jpg",
                "mimetype": "image\/jpeg",
                "filetype": "jpg",
                "pretty_type": "JPEG",
                "user": "UMJD8R3MX",
                "editable": false,
                "size": 23639,
                "mode": "hosted",
                "is_external": false,
                "external_type": "",
                "is_public": true,
                "public_url_shared": false,
                "display_as_bot": false,
                "username": "",
                "url_private": "https:\/\/files.slack.com\/files-pri\/TMQQCHQ8G-FR77H50RM\/img-20191201-wa0004.jpg?t=xoxe-738828602288-1172331074436-1172331081876-a36717768f1dfe08677b9dabda7bb52b",
                "url_private_download": "https:\/\/files.slack.com\/files-pri\/TMQQCHQ8G-FR77H50RM\/download\/img-20191201-wa0004.jpg?t=xoxe-738828602288-1172331074436-1172331081876-a36717768f1dfe08677b9dabda7bb52b",
                "thumb_64": "https:\/\/files.slack.com\/files-tmb\/TMQQCHQ8G-FR77H50RM-64f3dd96e0\/img-20191201-wa0004_64.jpg?t=xoxe-738828602288-1172331074436-1172331081876-a36717768f1dfe08677b9dabda7bb52b",
                "thumb_80": "https:\/\/files.slack.com\/files-tmb\/TMQQCHQ8G-FR77H50RM-64f3dd96e0\/img-20191201-wa0004_80.jpg?t=xoxe-738828602288-1172331074436-1172331081876-a36717768f1dfe08677b9dabda7bb52b",
                "thumb_360": "https:\/\/files.slack.com\/files-tmb\/TMQQCHQ8G-FR77H50RM-64f3dd96e0\/img-20191201-wa0004_360.jpg?t=xoxe-738828602288-1172331074436-1172331081876-a36717768f1dfe08677b9dabda7bb52b",
                "thumb_360_w": 360,
                "thumb_360_h": 269,
                "thumb_480": "https:\/\/files.slack.com\/files-tmb\/TMQQCHQ8G-FR77H50RM-64f3dd96e0\/img-20191201-wa0004_480.jpg?t=xoxe-738828602288-1172331074436-1172331081876-a36717768f1dfe08677b9dabda7bb52b",
                "thumb_480_w": 480,
                "thumb_480_h": 358,
                "thumb_160": "https:\/\/files.slack.com\/files-tmb\/TMQQCHQ8G-FR77H50RM-64f3dd96e0\/img-20191201-wa0004_160.jpg?t=xoxe-738828602288-1172331074436-1172331081876-a36717768f1dfe08677b9dabda7bb52b",
                "thumb_720": "https:\/\/files.slack.com\/files-tmb\/TMQQCHQ8G-FR77H50RM-64f3dd96e0\/img-20191201-wa0004_720.jpg?t=xoxe-738828602288-1172331074436-1172331081876-a36717768f1dfe08677b9dabda7bb52b",
                "thumb_720_w": 720,
                "thumb_720_h": 537,
                "image_exif_rotation": 1,
                "original_w": 791,
                "original_h": 590,
                "thumb_tiny": "AwAjADDTpOfalooAblvSl+b2pCT2pMtmgB3ze1LRRQAVWuY5Sd0bEj+7mrBzjjrSLuzz0oY07FZRN2KL\/wACNNcTkY+Uk\/3WOatNHkgjA\/CgLtXOBu9hSsJDYEdF\/eOWPp6VLSA5paY27hRRRQIKKKKACiiigD\/\/2Q==",
                "permalink": "https:\/\/com-s-309-project.slack.com\/files\/UMJD8R3MX\/FR77H50RM\/img-20191201-wa0004.jpg",
                "permalink_public": "https:\/\/slack-files.com\/TMQQCHQ8G-FR77H50RM-65a793ae27",
                "is_starred": false,
                "has_rich_preview": false
            }
        ],
        "upload": true,
        "user": "UMJD8R3MX",
        "display_as_bot": false,
        "ts": "1575248735.000100",
        "client_msg_id": "ae9bd85e-99ba-4cfb-8d7a-8f2df6e2c96d"
    }
]